Metadata-Version: 1.0
Name: hyperopt7777777name
Version: 0.0.1
Summary: test pypi
Home-page: https://github.com/RunxingZhong/stacking_automl_001
Author: zhongrunxinig
Author-email: zhongrunxing@gmail.com
License: MIT
Platform: UNKNOWN
